LandsatToolkit/__init__.py
LandsatToolkit/data_processor.py
LandsatToolkit/metadata_tools.py
LandsatToolkit/scene_tools.py
LandsatToolkit/utils.py
tests/__init__.py
tests/test_data_processor.py
tests/test_metadata_tools.py
tests/test_scene_tools.py
tests/test_utils.py
LandsatToolkit-1.0.0.dist-info/LICENSE
LandsatToolkit-1.0.0.dist-info/METADATA
LandsatToolkit-1.0.0.dist-info/WHEEL
LandsatToolkit-1.0.0.dist-info/top_level.txt
LandsatToolkit-1.0.0.dist-info/RECORD
