Metadata-Version: 2.1
Name: LandsatToolkit
Version: 1.0.0
Summary: A Python library for processing and analyzing satellite data.
Home-page: https://github.com/AmirDonyadide/LandsatToolkit
Author: Amirhossein Donyadidegan, Mohammad Kord Gholiabadi
Author-email: amirhossein.donyadidegan@mail.polimi.it, mohammad.kordgholiabad@mail.polimi.it
Keywords: satellite processing,remote sensing,GIS,raster data,satellite imagery,Landsat,LandsatToolkit
Classifier: Programming Language :: Python :: 3
Classifier: License :: OSI Approved :: MIT License
Classifier: Operating System :: OS Independent
Classifier: Intended Audience :: Developers
Classifier: Topic :: Scientific/Engineering :: GIS
Requires-Python: >=3.6
License-File: LICENSE
Requires-Dist: numpy>=1.19.0
Requires-Dist: rasterio>=1.2.0
Provides-Extra: dev
Requires-Dist: pytest>=6.0; extra == "dev"
Requires-Dist: sphinx>=4.0; extra == "dev"
Requires-Dist: black>=23.0; extra == "dev"
